<?xml version="1.0" encoding="utf-8" ?>
<dwsync>
<file name="alb-bg.jpg" server="100.42.52.207/dev.greentreeconsulting.cc/" local="131971746339456397" remote="131988112800000000" Dst="2" />
<file name="alb-bg@2x.jpg" server="100.42.52.207/dev.greentreeconsulting.cc/" local="131971746339476377" remote="131988112800000000" Dst="2" />
<file name="alb-map.jpg" server="100.42.52.207/dev.greentreeconsulting.cc/" local="131971746339486388" remote="131988112800000000" Dst="2" />
<file name="bao-bg@2x.jpg" server="100.42.52.207/dev.greentreeconsulting.cc/" local="131971746339536360" remote="131988112800000000" Dst="2" />
<file name="alb-map@2x.jpg" server="100.42.52.207/dev.greentreeconsulting.cc/" local="131971746339516373" remote="131988112800000000" Dst="2" />
<file name="bao-bg.jpg" server="100.42.52.207/dev.greentreeconsulting.cc/" local="131971746339526368" remote="131988112800000000" Dst="2" />
<file name="bao-map@2x.jpg" server="100.42.52.207/dev.greentreeconsulting.cc/" local="131971746339576323" remote="131988112800000000" Dst="2" />
<file name="bao-map.jpg" server="100.42.52.207/dev.greentreeconsulting.cc/" local="131971746339556331" remote="131988112800000000" Dst="2" />
<file name="edm-bg.jpg" server="100.42.52.207/dev.greentreeconsulting.cc/" local="131971746339596311" remote="131988112800000000" Dst="2" />
<file name="edm-bg@2x.jpg" server="100.42.52.207/dev.greentreeconsulting.cc/" local="131971746339606306" remote="131988112800000000" Dst="2" />
<file name="edm-map@2x.jpg" server="100.42.52.207/dev.greentreeconsulting.cc/" local="131971746339646278" remote="131988112800000000" Dst="2" />
<file name="edm-map.jpg" server="100.42.52.207/dev.greentreeconsulting.cc/" local="131971746339626293" remote="131988112800000000" Dst="2" />
<file name="ftw-bg.jpg" server="100.42.52.207/dev.greentreeconsulting.cc/" local="131971746339656280" remote="131988112800000000" Dst="2" />
<file name="ftw-bg@2x.jpg" server="100.42.52.207/dev.greentreeconsulting.cc/" local="131971746339676260" remote="131988112800000000" Dst="2" />
<file name="ftw-map.jpg" server="100.42.52.207/dev.greentreeconsulting.cc/" local="131971746339696248" remote="131988112800000000" Dst="2" />
<file name="ftw-map@2x.jpg" server="100.42.52.207/dev.greentreeconsulting.cc/" local="131971746339716238" remote="131988112800000000" Dst="2" />
<file name="hnv-bg.jpg" server="100.42.52.207/dev.greentreeconsulting.cc/" local="131971746339736227" remote="131988112800000000" Dst="2" />
<file name="hnv-bg@2x.jpg" server="100.42.52.207/dev.greentreeconsulting.cc/" local="131971746339746222" remote="131988112800000000" Dst="2" />
<file name="hnv-map.jpg" server="100.42.52.207/dev.greentreeconsulting.cc/" local="131971746339766203" remote="131988112800000000" Dst="2" />
<file name="hnv-map@2x.jpg" server="100.42.52.207/dev.greentreeconsulting.cc/" local="131971746339786195" remote="131988112800000000" Dst="2" />
<file name="jnk-bg.jpg" server="100.42.52.207/dev.greentreeconsulting.cc/" local="131971746339806188" remote="131988112800000000" Dst="2" />
<file name="jnk-map.jpg" server="100.42.52.207/dev.greentreeconsulting.cc/" local="131971746339836163" remote="131988112800000000" Dst="2" />
<file name="jnk-bg@2x.jpg" server="100.42.52.207/dev.greentreeconsulting.cc/" local="131971746339816172" remote="131988112800000000" Dst="2" />
<file name="jnk-map@2x.jpg" server="100.42.52.207/dev.greentreeconsulting.cc/" local="131971746339856149" remote="131988112800000000" Dst="2" />
<file name="klr-bg.jpg" server="100.42.52.207/dev.greentreeconsulting.cc/" local="131971746339876138" remote="131988112800000000" Dst="2" />
<file name="klr-bg@2x.jpg" server="100.42.52.207/dev.greentreeconsulting.cc/" local="131971746339886131" remote="131988112800000000" Dst="2" />
<file name="klr-map.jpg" server="100.42.52.207/dev.greentreeconsulting.cc/" local="131971746339906121" remote="131988112800000000" Dst="2" />
<file name="klr-map@2x.jpg" server="100.42.52.207/dev.greentreeconsulting.cc/" local="131971746339926109" remote="131988112800000000" Dst="2" />
<file name="mor-bg.jpg" server="100.42.52.207/dev.greentreeconsulting.cc/" local="131971746339946096" remote="131988112800000000" Dst="2" />
<file name="mor-map.jpg" server="100.42.52.207/dev.greentreeconsulting.cc/" local="131971746339986074" remote="131988112800000000" Dst="2" />
<file name="mor-bg@2x.jpg" server="100.42.52.207/dev.greentreeconsulting.cc/" local="131971746339976076" remote="131988112800000000" Dst="2" />
<file name="mor-map@2x.jpg" server="100.42.52.207/dev.greentreeconsulting.cc/" local="131971746340006050" remote="131988112800000000" Dst="2" />
<file name="mwc-bg.jpg" server="100.42.52.207/dev.greentreeconsulting.cc/" local="131971746340026053" remote="131988112800000000" Dst="2" />
<file name="mwc-bg@2x.jpg" server="100.42.52.207/dev.greentreeconsulting.cc/" local="131971746340036039" remote="131988112800000000" Dst="2" />
<file name="mwc-map.jpg" server="100.42.52.207/dev.greentreeconsulting.cc/" local="131971746340056027" remote="131988112800000000" Dst="2" />
<file name="mwc-map@2x.jpg" server="100.42.52.207/dev.greentreeconsulting.cc/" local="131971746340076014" remote="131988112800000000" Dst="2" />
<file name="noc-bg.jpg" server="100.42.52.207/dev.greentreeconsulting.cc/" local="131971746340096007" remote="131988113400000000" Dst="2" />
<file name="noc-bg@2x.jpg" server="100.42.52.207/dev.greentreeconsulting.cc/" local="131971746340105995" remote="131988113400000000" Dst="2" />
<file name="noc-map.jpg" server="100.42.52.207/dev.greentreeconsulting.cc/" local="131971746340125985" remote="131988113400000000" Dst="2" />
<file name="okc-bg.jpg" server="100.42.52.207/dev.greentreeconsulting.cc/" local="131971746340175954" remote="131988113400000000" Dst="2" />
<file name="okc-bg@2x.jpg" server="100.42.52.207/dev.greentreeconsulting.cc/" local="131971746340195976" remote="131988113400000000" Dst="2" />
<file name="noc-map@2x.jpg" server="100.42.52.207/dev.greentreeconsulting.cc/" local="131971746340155965" remote="131988113400000000" Dst="2" />
<file name="okc-map.jpg" server="100.42.52.207/dev.greentreeconsulting.cc/" local="131971746340215928" remote="131988113400000000" Dst="2" />
<file name="ows-bg.jpg" server="100.42.52.207/dev.greentreeconsulting.cc/" local="131971746340255903" remote="131988113400000000" Dst="2" />
<file name="okc-map@2x.jpg" server="100.42.52.207/dev.greentreeconsulting.cc/" local="131971746340235918" remote="131988113400000000" Dst="2" />
<file name="ows-bg@2x.jpg" server="100.42.52.207/dev.greentreeconsulting.cc/" local="131971746340265897" remote="131988113400000000" Dst="2" />
<file name="ows-map@2x.jpg" server="100.42.52.207/dev.greentreeconsulting.cc/" local="131971746340295873" remote="131988113400000000" Dst="2" />
<file name="ows-map.jpg" server="100.42.52.207/dev.greentreeconsulting.cc/" local="131971746340285887" remote="131988113400000000" Dst="2" />
<file name="soc-bg.jpg" server="100.42.52.207/dev.greentreeconsulting.cc/" local="131971746340315862" remote="131988113400000000" Dst="2" />
<file name="soc-bg@2x.jpg" server="100.42.52.207/dev.greentreeconsulting.cc/" local="131971746340335861" remote="131988113400000000" Dst="2" />
<file name="soc-map.jpg" server="100.42.52.207/dev.greentreeconsulting.cc/" local="131971746340355845" remote="131988113400000000" Dst="2" />
<file name="soc-map@2x.jpg" server="100.42.52.207/dev.greentreeconsulting.cc/" local="131971746340375820" remote="131988113400000000" Dst="2" />
<file name="sto-bg.jpg" server="100.42.52.207/dev.greentreeconsulting.cc/" local="131971746340395828" remote="131988113400000000" Dst="2" />
<file name="sto-bg@2x.jpg" server="100.42.52.207/dev.greentreeconsulting.cc/" local="131971746340405812" remote="131988113400000000" Dst="2" />
<file name="sto-map.jpg" server="100.42.52.207/dev.greentreeconsulting.cc/" local="131971746340435799" remote="131988113400000000" Dst="2" />
<file name="sto-map@2x.jpg" server="100.42.52.207/dev.greentreeconsulting.cc/" local="131971746340445786" remote="131988113400000000" Dst="2" />
<file name="stw-bg.jpg" server="100.42.52.207/dev.greentreeconsulting.cc/" local="131971746340475761" remote="131988113400000000" Dst="2" />
<file name="stw-map.jpg" server="100.42.52.207/dev.greentreeconsulting.cc/" local="131971746340515737" remote="131988113400000000" Dst="2" />
<file name="stw-bg@2x.jpg" server="100.42.52.207/dev.greentreeconsulting.cc/" local="131971746340505742" remote="131988113400000000" Dst="2" />
<file name="stw-map@2x.jpg" server="100.42.52.207/dev.greentreeconsulting.cc/" local="131971746340535722" remote="131988113400000000" Dst="2" />
<file name="tul-bg.jpg" server="100.42.52.207/dev.greentreeconsulting.cc/" local="131971746340545719" remote="131988113400000000" Dst="2" />
<file name="tul-bg@2x.jpg" server="100.42.52.207/dev.greentreeconsulting.cc/" local="131971746340565712" remote="131988113400000000" Dst="2" />
<file name="tul-map.jpg" server="100.42.52.207/dev.greentreeconsulting.cc/" local="131971746340575718" remote="131988113400000000" Dst="2" />
<file name="tul-map@2x.jpg" server="100.42.52.207/dev.greentreeconsulting.cc/" local="131971746340595693" remote="131988113400000000" Dst="2" />
<file name="wel-bg.jpg" server="100.42.52.207/dev.greentreeconsulting.cc/" local="131971746340615681" remote="131988113400000000" Dst="2" />
<file name="wel-bg@2x.jpg" server="100.42.52.207/dev.greentreeconsulting.cc/" local="131971746340645657" remote="131988113400000000" Dst="2" />
<file name="wel-map.jpg" server="100.42.52.207/dev.greentreeconsulting.cc/" local="131971746340665656" remote="131988113400000000" Dst="2" />
<file name="ykn-bg@2x.jpg" server="100.42.52.207/dev.greentreeconsulting.cc/" local="131971746340705626" remote="131988113400000000" Dst="2" />
<file name="ykn-bg.jpg" server="100.42.52.207/dev.greentreeconsulting.cc/" local="131971746340695632" remote="131988113400000000" Dst="2" />
<file name="wel-map@2x.jpg" server="100.42.52.207/dev.greentreeconsulting.cc/" local="131971746340685641" remote="131988113400000000" Dst="2" />
<file name="ykn-map.jpg" server="100.42.52.207/dev.greentreeconsulting.cc/" local="131971746340725614" remote="131988113400000000" Dst="2" />
<file name="ykn-map@2x.jpg" server="100.42.52.207/dev.greentreeconsulting.cc/" local="131971746340735607" remote="131988113400000000" Dst="2" />
</dwsync>